funchacks/__init__.py
funchacks/errors.py
funchacks/impl.py
funchacks/inspections.py
funchacks/typehints.py
funchacks/interfaces/__init__.py
funchacks/interfaces/collections.py
funchacks/internal/__init__.py
funchacks/internal/generics.py
funchacks/internal/misc.py
funchacks/sig/__init__.py
funchacks/sig/impl.py
funchacks/sig/localvars.py
funchacks/sig/marks.py
funchacks-1.0.1.dist-info/LICENSE.md
funchacks-1.0.1.dist-info/METADATA
funchacks-1.0.1.dist-info/WHEEL
funchacks-1.0.1.dist-info/top_level.txt
funchacks-1.0.1.dist-info/RECORD
