Metadata-Version: 2.1
Name: funchacks
Version: 1.0.1
Summary: UNKNOWN
Home-page: https://github.com/Animatea/funchacks
Author: DenyS
License: Apache License, Version 2.0
Download-URL: https://github.com/Animatea/funchacks/archive/refs/heads/main.zip
Project-URL: GitHub, https://github.com/Animatea/funchacks
Project-URL: Bug Tracker, https://github.com/Animatea/funchacks/issues
Keywords: FUNCTIONAL PROGRAMMING,FUNCTION TOOLS,FUNCTION UTILS,UTILS
Platform: UNKNOWN
Classifier: Programming Language :: Python :: 3.8
Classifier: Programming Language :: Python :: 3.9
Classifier: Intended Audience :: Developers
Classifier: Topic :: Software Development :: Libraries :: Python Modules
Classifier: Topic :: Software Development :: Libraries
Classifier: Programming Language :: Python :: Implementation :: CPython
Classifier: License :: OSI Approved :: Apache Software License
Classifier: Intended Audience :: Other Audience
Classifier: Typing :: Typed
Classifier: Natural Language :: English
Classifier: Operating System :: OS Independent
Classifier: Topic :: Utilities
Requires-Python: >=3.8
License-File: LICENSE.md
